README.md
setup.cfg
setup.py
cronitor/__init__.py
cronitor/__main__.py
cronitor/monitor.py
cronitor/test/__init__.py
cronitor/test/test_monitor.py
cronitor/test/test_ping_api.py
cronitor_alias.egg-info/PKG-INFO
cronitor_alias.egg-info/SOURCES.txt
cronitor_alias.egg-info/dependency_links.txt
cronitor_alias.egg-info/entry_points.txt
cronitor_alias.egg-info/requires.txt
cronitor_alias.egg-info/top_level.txt